shadowdns
