Metadata-Version: 1.1
Name: shadowdns
Version: 0.1.3
Summary: A DNS forwarder using Shadowsocks as the server
Home-page: https://github.com/clowwindy/shadowdns
Author: clowwindy
Author-email: clowwindy42@gmail.com
License: MIT
Platform: UNKNOWN
Classifier: License :: OSI Approved :: MIT License
Classifier: Programming Language :: Python :: 2
Classifier: Programming Language :: Python :: 2.6
Classifier: Programming Language :: Python :: 2.7
Classifier: Topic :: Internet :: Proxy Servers
